README.rst
setup.cfg
setup.py
pyspool.egg-info/PKG-INFO
pyspool.egg-info/SOURCES.txt
pyspool.egg-info/dependency_links.txt
pyspool.egg-info/requires.txt
pyspool.egg-info/top_level.txt
spool/__init__.py
spool/file.py
spool/ownership.py
spool/spool.py
spool/spoolex.py
spool/spoolverb.py
spool/utils.py
spool/wallet.py