Metadata-Version: 1.1
Name: pyspool
Version: 0.2.0
Summary: pyspool: Reference implementation of the SPOOL protocol
Home-page: https://github.com/ascribe/pyspool
Author: pyspool contributors
Author-email: devel@ascribe.io
License: Apache Software License
Platform: UNKNOWN
Classifier: Development Status :: 3 - Alpha
Classifier: Intended Audience :: Developers
Classifier: Natural Language :: English
Classifier: License :: OSI Approved :: Apache Software License
Classifier: Programming Language :: Python :: 2
Classifier: Programming Language :: Python :: 2.7
Classifier: Programming Language :: Python :: 3
Classifier: Programming Language :: Python :: 3.5
Classifier: Topic :: Software Development
